berremueller/__init__.py
berremueller/berreman_mueller.py
berremueller/cholesteric.py
berremueller/dielectric_tensor.py
berremueller/field_plotting.py
berremueller/full_berreman.py
berremueller/mueller.py
berremueller/pyllama.py
berremueller/python_util.py
berremueller-1.1.1.dist-info/LICENSE
berremueller-1.1.1.dist-info/METADATA
berremueller-1.1.1.dist-info/WHEEL
berremueller-1.1.1.dist-info/top_level.txt
berremueller-1.1.1.dist-info/RECORD
