Metadata-Version: 2.1
Name: berremueller
Version: 1.1.1
Summary: A library for implementing the Berreman 4X4 matrix method alongside Mueller matrices
Author-email: Andrew Salij <andrewsalij@gmail.com>
License-File: LICENSE
Requires-Dist: numpy
Requires-Dist: matplotlib
Requires-Dist: scipy
Requires-Dist: sympy
Requires-Dist: pandas
